TriTan/__init__.py
TriTan/tritan_module.py
TriTan-1.1.8.dist-info/LICENSE.txt
TriTan-1.1.8.dist-info/METADATA
TriTan-1.1.8.dist-info/WHEEL
TriTan-1.1.8.dist-info/top_level.txt
TriTan-1.1.8.dist-info/RECORD
